README.md
setup.py
poc.parser.egg-info/PKG-INFO
poc.parser.egg-info/SOURCES.txt
poc.parser.egg-info/dependency_links.txt
poc.parser.egg-info/requires.txt
poc.parser.egg-info/top_level.txt
poc_parser/__init__.py
poc_parser/expression.py
poc_parser/gtlog.py
poc_parser/main.py
poc_parser/proxychainwrap.sh
poc_parser/utils.py
poc_parser/thirdparty_packages/__init__.py
poc_parser/thirdparty_packages/requests/__init__.py
poc_parser/thirdparty_packages/requests/__version__.py
poc_parser/thirdparty_packages/requests/_internal_utils.py
poc_parser/thirdparty_packages/requests/adapters.py
poc_parser/thirdparty_packages/requests/api.py
poc_parser/thirdparty_packages/requests/auth.py
poc_parser/thirdparty_packages/requests/certs.py
poc_parser/thirdparty_packages/requests/compat.py
poc_parser/thirdparty_packages/requests/cookies.py
poc_parser/thirdparty_packages/requests/dump.py
poc_parser/thirdparty_packages/requests/exceptions.py
poc_parser/thirdparty_packages/requests/help.py
poc_parser/thirdparty_packages/requests/hooks.py
poc_parser/thirdparty_packages/requests/models.py
poc_parser/thirdparty_packages/requests/packages.py
poc_parser/thirdparty_packages/requests/sessions.py
poc_parser/thirdparty_packages/requests/status_codes.py
poc_parser/thirdparty_packages/requests/structures.py
poc_parser/thirdparty_packages/requests/utils.py