Metadata-Version: 2.1
Name: poc.parser
Version: 1.1.2
Summary: poc framework
Home-page: UNKNOWN
Author: 
Author-email: 
License: UNKNOWN
Platform: UNKNOWN
Classifier: Programming Language :: Python :: 3
Requires-Python: >=3.6
